{
  "name": "Ayush Sharma",
  "github": "Im-Ayushh",
  "program": "B.Tech CSE",
  "campus": "Amity University Noida",
  "skills": ["python", "javascript", "react", "SQL", "Html-Css"],
  "interests": ["agents", "NLP", "AI"],
  "my_twin": "I would track my study focus and energy levels throughout the day — I notice I'm sharp in the morning but crash after lunch, and I want to correlate that with my sleep the night before and what I ate, so I can actually fix it instead of just complaining about it."
}
